[
  {
    "id": 1763223827285,
    "departmentId": 1,
    "rating": "Unsatisfying",
    "comment": "",
    "createdAt": "2025-11-15T16:23:47.285Z"
  },
  {
    "id": 1763224273502,
    "departmentId": 1763224258731,
    "rating": "Satisfying",
    "comment": "",
    "createdAt": "2025-11-15T16:31:13.502Z"
  },
  {
    "id": 1763224294289,
    "departmentId": 1763224258731,
    "rating": "Neutral",
    "comment": "",
    "createdAt": "2025-11-15T16:31:34.289Z"
  },
  {
    "id": 1763542107256,
    "departmentId": 3,
    "rating": "Excellent",
    "comment": "Test",
    "createdAt": "2025-11-19T08:48:27.256Z"
  },
  {
    "id": 1763720392636,
    "departmentId": 3,
    "rating": "Neutral",
    "comment": "fsdjbkubzuiwe;bvj;sbaljv",
    "createdAt": "2025-11-21T10:19:52.636Z"
  },
  {
    "id": 1763720490619,
    "departmentId": 3,
    "rating": "Satisfying",
    "comment": "as.klanldbaiasc\n",
    "createdAt": "2025-11-21T10:21:30.619Z"
  },
  {
    "id": 1763720528331,
    "departmentId": 3,
    "rating": "Unsatisfying",
    "comment": "asjdbivfsvbcsboia",
    "createdAt": "2025-11-21T10:22:08.331Z"
  },
  {
    "id": 1763720739636,
    "departmentId": 3,
    "rating": "Satisfying",
    "comment": "sasdadas",
    "createdAt": "2025-11-21T10:25:39.636Z"
  },
  {
    "id": 1763720778391,
    "departmentId": 3,
    "rating": "Unsatisfying",
    "comment": "",
    "createdAt": "2025-11-21T10:26:18.391Z"
  },
  {
    "id": 1763747916893,
    "departmentId": 3,
    "rating": "Neutral",
    "comment": "test",
    "createdAt": "2025-11-21T17:58:36.893Z"
  }
]